pykoopman_ae/__init__.py
pykoopman_ae/autoencoder.py
pykoopman_ae/dataset_generator.py
pykoopman_ae/default_params.py
pykoopman_ae/model_io.py
pykoopman_ae/params_test.py
pykoopman_ae/system_extraction.py
pykoopman_ae/training.py
pykoopman_ae-0.1.2.dist-info/LICENSE
pykoopman_ae-0.1.2.dist-info/METADATA
pykoopman_ae-0.1.2.dist-info/WHEEL
pykoopman_ae-0.1.2.dist-info/top_level.txt
pykoopman_ae-0.1.2.dist-info/RECORD
